[
	{
		"img_path": "1.png",
		"xyz": [
			1766.74,
			-1089.17,
			960.96
		],
		"orient": [
			0.1738,-0.69496,0.21776,0.66288
		]
	},
	{
		"img_path": "2.png",
		"xyz": [
			1909.28,
			-766.33,
			1075.17
		],
		"orient": [
			0.10458,-0.77213,0.17165,0.60284
		]
	},
	{
		"img_path": "3.png",
		"xyz": [
			1971.07,
			-539.88,
			1111.63
		],
		"orient": [
			0.07884,-0.71187,0.11482,0.68836
		]
	},
	{
		"img_path": "4.png",
		"xyz": [
			1889.71,
			-514.84,
			1134.16
		],
		"orient": [
			0.08822,-0.61118,0.09657,0.78061
		]
	},
	{
		"img_path": "5.png",
		"xyz": [
			1706.12,
			-834.53,
			1342.29
		],
		"orient": [
			0.15308,-0.64727,0.16583,0.72808
		]
	},
	{
		"img_path": "6.png",
		"xyz": [
			1614.17,
			-772.72,
			1469.22
		],
		"orient": [
			0.09792,-0.62820,0.19566,0.74666
		]
	},
	{
		"img_path": "7.png",
		"xyz": [
			1682.31,
			-444.25,
			1508.84
		],
		"orient": [
			0.21025,-0.65064,0.0,0.72970
		]
	}
]